etape/__init__.py
etape/_version.py
etape/etape.py
odessa_etape-0.1.dist-info/DESCRIPTION.rst
odessa_etape-0.1.dist-info/METADATA
odessa_etape-0.1.dist-info/metadata.json
odessa_etape-0.1.dist-info/RECORD
odessa_etape-0.1.dist-info/top_level.txt
odessa_etape-0.1.dist-info/WHEEL
