Metadata-Version: 2.0
Name: odessa-etape
Version: 0.1
Summary: ODESSA ETAPE protocol
Home-page: http://herve.niderb.fr/
Author: Hervé Bredin
Author-email: bredin@limsi.fr
License: UNKNOWN
Platform: UNKNOWN
Classifier: Development Status :: 4 - Beta
Classifier: Intended Audience :: Science/Research
Classifier: License :: OSI Approved :: MIT License
Classifier: Natural Language :: English
Classifier: Programming Language :: Python :: 2
Classifier: Programming Language :: Python :: 2.7
Classifier: Programming Language :: Python :: 3
Classifier: Programming Language :: Python :: 3.4
Classifier: Programming Language :: Python :: 3.5
Classifier: Topic :: Scientific/Engineering
Requires-Dist: pyannote.core (>=0.6.3)
Requires-Dist: pyannote.metrics (>=0.7)
Requires-Dist: pyannote.parser (>=0.4.2)
Requires-Dist: pyannote.features (>=0.2.1)
